README.md
setup.cfg
setup.py
api/__init__.py
api/api.py
besc.egg-info/PKG-INFO
besc.egg-info/SOURCES.txt
besc.egg-info/dependency_links.txt
besc.egg-info/requires.txt
besc.egg-info/top_level.txt
model/__init__.py
model/device.py
model/keypair.py
model/project_data.py
services/__init__.py
services/besc_host.py
utils/__init__.py
utils/dateConvert.py
utils/validate.py