Metadata-Version: 1.1
Name: besc
Version: 1.0.1
Summary: Send data to the ESS API
Home-page: UNKNOWN
Author: Clive Lim
Author-email: UNKNOWN
License: MIT License
Download-URL: https://github.com/rock98rock/BESC-ESS-API-DEV/archive/1.0.tar.gz
Platform: UNKNOWN
